baza/__init__.py
baza-0.0.1.dist-info/WHEEL
baza-0.0.1.dist-info/METADATA
baza-0.0.1.dist-info/RECORD
