Metadata-Version: 2.1
Name: baza
Version: 0.0.1
Summary: baza it's a tool for easy database connection switching.
Author-email: Arkadiusz Halicki <halicki.arkadiusz@gmail.com>
Project-URL: Home, https://github.com/halicki/baza
